smad/__init__.py
smad/main.py
smad-0.0.1.dist-info/LICENSE
smad-0.0.1.dist-info/METADATA
smad-0.0.1.dist-info/WHEEL
smad-0.0.1.dist-info/top_level.txt
smad-0.0.1.dist-info/RECORD
